napari_simpleitk_image_processing/__init__.py
napari_simpleitk_image_processing/_bia_bob_plugins.py
napari_simpleitk_image_processing/_function.py
napari_simpleitk_image_processing/_simpleitk_image_processing.py
napari_simpleitk_image_processing/_tests/__init__.py
napari_simpleitk_image_processing/_tests/test_function.py
napari_simpleitk_image_processing-0.4.9.dist-info/LICENSE
napari_simpleitk_image_processing-0.4.9.dist-info/METADATA
napari_simpleitk_image_processing-0.4.9.dist-info/WHEEL
napari_simpleitk_image_processing-0.4.9.dist-info/entry_points.txt
napari_simpleitk_image_processing-0.4.9.dist-info/top_level.txt
napari_simpleitk_image_processing-0.4.9.dist-info/RECORD
