Metadata-Version: 2.1
Name: napari-simpleitk-image-processing
Version: 0.4.9
Summary: Process and analyze images using SimpleITK in napari
Home-page: https://github.com/haesleinhuepf/napari-simpleitk-image-processing
Author: Robert Haase
Author-email: robert.haase@tu-dresden.de
License: BSD-3-Clause
Project-URL: Bug Tracker, https://github.com/haesleinhuepf/napari-simpleitk-image-processing/issues
Project-URL: Documentation, https://github.com/haesleinhuepf/napari-simpleitk-image-processing#README.md
Project-URL: Source Code, https://github.com/haesleinhuepf/napari-simpleitk-image-processing
Project-URL: User Support, https://github.com/haesleinhuepf/napari-simpleitk-image-processing/issues
Classifier: Development Status :: 3 - Alpha
Classifier: Intended Audience :: Science/Research
Classifier: Framework :: napari
Classifier: Topic :: Scientific/Engineering :: Image Processing
Classifier: Topic :: Scientific/Engineering :: Information Analysis
Classifier: Programming Language :: Python
Classifier: Programming Language :: Python :: 3
Classifier: Programming Language :: Python :: 3.8
Classifier: Programming Language :: Python :: 3.9
Classifier: Programming Language :: Python :: 3.10
Classifier: Operating System :: OS Independent
Classifier: License :: OSI Approved :: BSD License
Requires-Python: >=3.8
License-File: LICENSE
Requires-Dist: napari-plugin-engine>=0.1.4
Requires-Dist: numpy
Requires-Dist: simpleitk
Requires-Dist: napari-tools-menu>=0.1.17
Requires-Dist: napari-time-slicer
Requires-Dist: napari-skimage-regionprops>=0.5.1
Requires-Dist: napari-assistant>=0.3.10
Requires-Dist: pandas
Requires-Dist: stackview>=0.3.2
